azure/ai/transcription/__init__.py
azure/ai/transcription/_client.py
azure/ai/transcription/_configuration.py
azure/ai/transcription/_patch.py
azure/ai/transcription/_version.py
azure/ai/transcription/py.typed
azure/ai/transcription/_operations/__init__.py
azure/ai/transcription/_operations/_operations.py
azure/ai/transcription/_operations/_patch.py
azure/ai/transcription/_utils/__init__.py
azure/ai/transcription/_utils/model_base.py
azure/ai/transcription/_utils/serialization.py
azure/ai/transcription/_utils/utils.py
azure/ai/transcription/aio/__init__.py
azure/ai/transcription/aio/_client.py
azure/ai/transcription/aio/_configuration.py
azure/ai/transcription/aio/_patch.py
azure/ai/transcription/aio/_operations/__init__.py
azure/ai/transcription/aio/_operations/_operations.py
azure/ai/transcription/aio/_operations/_patch.py
azure/ai/transcription/models/__init__.py
azure/ai/transcription/models/_enums.py
azure/ai/transcription/models/_models.py
azure/ai/transcription/models/_patch.py
azure_ai_transcription-1.0.0b2.dist-info/licenses/LICENSE
azure_ai_transcription-1.0.0b2.dist-info/METADATA
azure_ai_transcription-1.0.0b2.dist-info/WHEEL
azure_ai_transcription-1.0.0b2.dist-info/top_level.txt
azure_ai_transcription-1.0.0b2.dist-info/RECORD
